{
  "slug": "bensley-joseph-1",
  "name": "Bensley Joseph",
  "seasons": [
    {
      "season": "2021-22",
      "team": "Miami (FL)",
      "conf": "ACC",
      "gp": 36,
      "gs": 0,
      "mp_g": 13.3333333333,
      "fg_pct": 0.3466666667,
      "fg3_pct": 0.3947368421,
      "ft_pct": 0.8333333333,
      "orb_g": 0.2777777778,
      "drb_g": 1.3333333333,
      "trb_g": 1.6111111111,
      "ast_g": 0.7777777778,
      "stl_g": 0.4444444444,
      "blk_g": 0.0833333333,
      "tov_g": 0.6944444444,
      "pf_g": 1.1666666667,
      "pts_g": 2.2777777778
    },
    {
      "season": "2022-23",
      "team": "Miami (FL)",
      "conf": "ACC",
      "gp": 37,
      "gs": 2,
      "mp_g": 19.972972973,
      "fg_pct": 0.417218543,
      "fg3_pct": 0.3977272727,
      "ft_pct": 0.693877551,
      "orb_g": 0.3513513514,
      "drb_g": 1.7027027027,
      "trb_g": 2.0540540541,
      "ast_g": 2.027027027,
      "stl_g": 0.6216216216,
      "blk_g": 0.3243243243,
      "tov_g": 1.1351351351,
      "pf_g": 1.7837837838,
      "pts_g": 5.2702702703
    },
    {
      "season": "2023-24",
      "team": "Miami (FL)",
      "conf": "ACC",
      "gp": 32,
      "gs": 27,
      "mp_g": 31.46875,
      "fg_pct": 0.4075471698,
      "fg3_pct": 0.3636363636,
      "ft_pct": 0.78,
      "orb_g": 0.53125,
      "drb_g": 2.875,
      "trb_g": 3.40625,
      "ast_g": 3.4375,
      "stl_g": 1.5,
      "blk_g": 0.6875,
      "tov_g": 2.15625,
      "pf_g": 2.28125,
      "pts_g": 9.59375
    },
    {
      "season": "2024-25",
      "team": "Providence",
      "conf": "Big East",
      "gp": 32,
      "gs": 27,
      "mp_g": 29.78125,
      "fg_pct": 0.4227405248,
      "fg3_pct": 0.3978494624,
      "ft_pct": 0.7402597403,
      "orb_g": 0.46875,
      "drb_g": 3.59375,
      "trb_g": 4.0625,
      "ast_g": 3.15625,
      "stl_g": 1.25,
      "blk_g": 0.09375,
      "tov_g": 2.1875,
      "pf_g": 2.5,
      "pts_g": 13.15625
    }
  ],
  "source": "https://www.sports-reference.com/cbb/players/bensley-joseph-1.html",
  "last_scraped": "2025-11-01T00:31:27.938Z"
}