{
  "slug": "cameron-fens-1",
  "name": "Cameron Fens",
  "seasons": [
    {
      "season": "2022-23",
      "team": "Illinois–Chicago",
      "conf": "MVC",
      "gp": 31,
      "gs": 12,
      "mp_g": 10.935483871,
      "fg_pct": 0.4912280702,
      "fg3_pct": null,
      "ft_pct": 0.488372093,
      "orb_g": 0.8064516129,
      "drb_g": 1.6129032258,
      "trb_g": 2.4193548387,
      "ast_g": 0.2258064516,
      "stl_g": 0.2580645161,
      "blk_g": 0.8709677419,
      "tov_g": 0.6129032258,
      "pf_g": 1.0967741935,
      "pts_g": 2.4838709677
    },
    {
      "season": "2023-24",
      "team": "Illinois–Chicago",
      "conf": "MVC",
      "gp": 21,
      "gs": 3,
      "mp_g": 5.4285714286,
      "fg_pct": 0.6785714286,
      "fg3_pct": null,
      "ft_pct": 0.5294117647,
      "orb_g": 0.7619047619,
      "drb_g": 1.2857142857,
      "trb_g": 2.0476190476,
      "ast_g": 0.1428571429,
      "stl_g": 0.0952380952,
      "blk_g": 0.5238095238,
      "tov_g": 0.2857142857,
      "pf_g": 0.6666666667,
      "pts_g": 2.2380952381
    },
    {
      "season": "2024-25",
      "team": "South Dakota",
      "conf": "Summit",
      "gp": 19,
      "gs": 16,
      "mp_g": 18.3684210526,
      "fg_pct": 0.5675675676,
      "fg3_pct": 0,
      "ft_pct": 0.5873015873,
      "orb_g": 2.2631578947,
      "drb_g": 2.7368421053,
      "trb_g": 5,
      "ast_g": 0.4210526316,
      "stl_g": 0.3157894737,
      "blk_g": 1.1052631579,
      "tov_g": 0.8421052632,
      "pf_g": 2,
      "pts_g": 8.5789473684
    }
  ],
  "source": "https://www.sports-reference.com/cbb/players/cameron-fens-1.html",
  "last_scraped": "2025-11-01T16:54:12.503Z"
}