{
  "slug": "cole-hargrove-1",
  "name": "Cole Hargrove",
  "seasons": [
    {
      "season": "2022-23",
      "team": "Drexel",
      "conf": "CAA",
      "gp": 18,
      "gs": 0,
      "mp_g": 3.7777777778,
      "fg_pct": 0.5,
      "fg3_pct": 0,
      "ft_pct": 0.5,
      "orb_g": 0.4444444444,
      "drb_g": 0.5555555556,
      "trb_g": 1,
      "ast_g": 0.2222222222,
      "stl_g": 0.2777777778,
      "blk_g": 0.1111111111,
      "tov_g": 0.1111111111,
      "pf_g": 0.4444444444,
      "pts_g": 1.1111111111
    },
    {
      "season": "2023-24",
      "team": "Drexel",
      "conf": "CAA",
      "gp": 16,
      "gs": 0,
      "mp_g": 4.1875,
      "fg_pct": 0.5,
      "fg3_pct": 0,
      "ft_pct": 0.5,
      "orb_g": 0.125,
      "drb_g": 0.8125,
      "trb_g": 0.9375,
      "ast_g": 0.1875,
      "stl_g": 0.0625,
      "blk_g": 0.5625,
      "tov_g": 0.125,
      "pf_g": 0.75,
      "pts_g": 0.9375
    },
    {
      "season": "2024-25",
      "team": "Drexel",
      "conf": "CAA",
      "gp": 33,
      "gs": 33,
      "mp_g": 32.5151515152,
      "fg_pct": 0.5862068966,
      "fg3_pct": 0.2068965517,
      "ft_pct": 0.6756756757,
      "orb_g": 3.0303030303,
      "drb_g": 4.4545454545,
      "trb_g": 7.4848484848,
      "ast_g": 1.7272727273,
      "stl_g": 0.6666666667,
      "blk_g": 1.8484848485,
      "tov_g": 1.1212121212,
      "pf_g": 2.3333333333,
      "pts_g": 9.9393939394
    }
  ],
  "source": "https://www.sports-reference.com/cbb/players/cole-hargrove-1.html",
  "last_scraped": "2025-11-01T13:50:26.220Z"
}