{
  "slug": "derek-simpson-1",
  "name": "Derek Simpson",
  "seasons": [
    {
      "season": "2022-23",
      "team": "Rutgers",
      "conf": "Big Ten",
      "gp": 34,
      "gs": 6,
      "mp_g": 20.1176470588,
      "fg_pct": 0.3739837398,
      "fg3_pct": 0.2166666667,
      "ft_pct": 0.7931034483,
      "orb_g": 0.4411764706,
      "drb_g": 1.1764705882,
      "trb_g": 1.6176470588,
      "ast_g": 1.4705882353,
      "stl_g": 0.7647058824,
      "blk_g": 0.0882352941,
      "tov_g": 0.9117647059,
      "pf_g": 1.2058823529,
      "pts_g": 7.1470588235
    },
    {
      "season": "2023-24",
      "team": "Rutgers",
      "conf": "Big Ten",
      "gp": 32,
      "gs": 25,
      "mp_g": 25.96875,
      "fg_pct": 0.3052631579,
      "fg3_pct": 0.2816901408,
      "ft_pct": 0.8641975309,
      "orb_g": 0.84375,
      "drb_g": 2.34375,
      "trb_g": 3.1875,
      "ast_g": 2.90625,
      "stl_g": 1.375,
      "blk_g": 0.0625,
      "tov_g": 1.5,
      "pf_g": 1.28125,
      "pts_g": 8.25
    },
    {
      "season": "2024-25",
      "team": "Saint Joseph's",
      "conf": "A-10",
      "gp": 35,
      "gs": 22,
      "mp_g": 30,
      "fg_pct": 0.3505154639,
      "fg3_pct": 0.3076923077,
      "ft_pct": 0.7702702703,
      "orb_g": 1.0285714286,
      "drb_g": 2.8285714286,
      "trb_g": 3.8571428571,
      "ast_g": 3.6,
      "stl_g": 0.9714285714,
      "blk_g": 0.1428571429,
      "tov_g": 1.6857142857,
      "pf_g": 1.6571428571,
      "pts_g": 8.7142857143
    }
  ],
  "source": "https://www.sports-reference.com/cbb/players/derek-simpson-1.html",
  "last_scraped": "2025-11-01T04:40:39.351Z"
}