{
  "slug": "devan-sapp-1",
  "name": "Devan Sapp",
  "seasons": [
    {
      "season": "2021-22",
      "team": "Did not play - juco",
      "conf": "—",
      "gp": null,
      "gs": null,
      "mp_g": null,
      "fg_pct": null,
      "fg3_pct": null,
      "ft_pct": null,
      "orb_g": null,
      "drb_g": null,
      "trb_g": null,
      "ast_g": null,
      "stl_g": null,
      "blk_g": null,
      "tov_g": null,
      "pf_g": null,
      "pts_g": null
    },
    {
      "season": "2022-23",
      "team": "UMBC",
      "conf": "AEC",
      "gp": 22,
      "gs": 0,
      "mp_g": 7.2272727273,
      "fg_pct": 0.380952381,
      "fg3_pct": 0.275862069,
      "ft_pct": 0.75,
      "orb_g": 0.3181818182,
      "drb_g": 0.5454545455,
      "trb_g": 0.8636363636,
      "ast_g": 0.2727272727,
      "stl_g": 0.1363636364,
      "blk_g": 0,
      "tov_g": 0.1818181818,
      "pf_g": 0.7272727273,
      "pts_g": 2.0909090909
    },
    {
      "season": "2023-24",
      "team": "UMBC",
      "conf": "AEC",
      "gp": 32,
      "gs": 25,
      "mp_g": 16.65625,
      "fg_pct": 0.3833333333,
      "fg3_pct": 0.3902439024,
      "ft_pct": 0.5,
      "orb_g": 0.71875,
      "drb_g": 1.84375,
      "trb_g": 2.5625,
      "ast_g": 0.53125,
      "stl_g": 0.5625,
      "blk_g": 0.0625,
      "tov_g": 0.875,
      "pf_g": 1.40625,
      "pts_g": 3.9375
    },
    {
      "season": "2024-25",
      "team": "UMBC",
      "conf": "AEC",
      "gp": 31,
      "gs": 6,
      "mp_g": 12.0322580645,
      "fg_pct": 0.3826086957,
      "fg3_pct": 0.3108108108,
      "ft_pct": 0.8181818182,
      "orb_g": 0.2903225806,
      "drb_g": 0.9032258065,
      "trb_g": 1.1935483871,
      "ast_g": 0.5161290323,
      "stl_g": 0.2580645161,
      "blk_g": 0,
      "tov_g": 0.5483870968,
      "pf_g": 0.9032258065,
      "pts_g": 3.8709677419
    }
  ],
  "source": "https://www.sports-reference.com/cbb/players/devan-sapp-1.html",
  "last_scraped": "2025-11-01T04:40:42.714Z"
}