{
  "slug": "eugene-browniii-1",
  "name": "Eugene Brown III",
  "seasons": [
    {
      "season": "2020-21",
      "team": "Ohio State",
      "conf": "Big Ten",
      "gp": 29,
      "gs": 0,
      "mp_g": 6.1724137931,
      "fg_pct": 0.3513513514,
      "fg3_pct": 0.28,
      "ft_pct": 0.5,
      "orb_g": 0.3103448276,
      "drb_g": 0.9655172414,
      "trb_g": 1.275862069,
      "ast_g": 0.2068965517,
      "stl_g": 0.1034482759,
      "blk_g": 0.1379310345,
      "tov_g": 0.1379310345,
      "pf_g": 0.3448275862,
      "pts_g": 1.2068965517
    },
    {
      "season": "2021-22",
      "team": "Ohio State",
      "conf": "Big Ten",
      "gp": 26,
      "gs": 10,
      "mp_g": 16.9615384615,
      "fg_pct": 0.4415584416,
      "fg3_pct": 0.2285714286,
      "ft_pct": 0.6086956522,
      "orb_g": 0.7307692308,
      "drb_g": 1.6923076923,
      "trb_g": 2.4230769231,
      "ast_g": 0.5384615385,
      "stl_g": 0.1923076923,
      "blk_g": 0.2692307692,
      "tov_g": 0.5384615385,
      "pf_g": 1.6153846154,
      "pts_g": 3.4615384615
    },
    {
      "season": "2022-23",
      "team": "Ohio State",
      "conf": "Big Ten",
      "gp": 22,
      "gs": 1,
      "mp_g": 10.0909090909,
      "fg_pct": 0.53125,
      "fg3_pct": 0.375,
      "ft_pct": 0.6666666667,
      "orb_g": 0.4090909091,
      "drb_g": 1.1363636364,
      "trb_g": 1.5454545455,
      "ast_g": 0.1818181818,
      "stl_g": 0.4090909091,
      "blk_g": 0.2727272727,
      "tov_g": 0.4090909091,
      "pf_g": 1.4090909091,
      "pts_g": 2.1818181818
    },
    {
      "season": "2023-24",
      "team": "Georgia Southern",
      "conf": "Sun Belt",
      "gp": 23,
      "gs": 21,
      "mp_g": 25.8695652174,
      "fg_pct": 0.4487179487,
      "fg3_pct": 0.3611111111,
      "ft_pct": 0.8305084746,
      "orb_g": 1.4347826087,
      "drb_g": 3.7826086957,
      "trb_g": 5.2173913043,
      "ast_g": 0.8260869565,
      "stl_g": 0.9565217391,
      "blk_g": 0.6956521739,
      "tov_g": 1.3913043478,
      "pf_g": 2.1304347826,
      "pts_g": 9.347826087
    },
    {
      "season": "2024-25",
      "team": "Georgia Southern",
      "conf": "Sun Belt",
      "gp": 29,
      "gs": 23,
      "mp_g": 24.2068965517,
      "fg_pct": 0.3518518519,
      "fg3_pct": 0.297029703,
      "ft_pct": 0.72,
      "orb_g": 1.1379310345,
      "drb_g": 2.6551724138,
      "trb_g": 3.7931034483,
      "ast_g": 0.724137931,
      "stl_g": 0.6206896552,
      "blk_g": 0.275862069,
      "tov_g": 0.9655172414,
      "pf_g": 1.6551724138,
      "pts_g": 5.5862068966
    }
  ],
  "source": "https://www.sports-reference.com/cbb/players/eugene-browniii-1.html",
  "last_scraped": "2025-11-01T16:55:06.432Z"
}