{
  "slug": "evan-wilson-1",
  "name": "Evan Wilson",
  "seasons": [
    {
      "season": "2021-22",
      "team": "Akron",
      "conf": "MAC",
      "gp": 6,
      "gs": 0,
      "mp_g": 2.3333333333,
      "fg_pct": 0.25,
      "fg3_pct": 0,
      "ft_pct": null,
      "orb_g": 0,
      "drb_g": 0,
      "trb_g": 0,
      "ast_g": 0.3333333333,
      "stl_g": 0.1666666667,
      "blk_g": 0,
      "tov_g": 0,
      "pf_g": 0.1666666667,
      "pts_g": 0.3333333333
    },
    {
      "season": "2022-23",
      "team": "Akron",
      "conf": "MAC",
      "gp": 13,
      "gs": 0,
      "mp_g": 2.6153846154,
      "fg_pct": 0.4166666667,
      "fg3_pct": 0.5,
      "ft_pct": 0,
      "orb_g": 0,
      "drb_g": 0.0769230769,
      "trb_g": 0.0769230769,
      "ast_g": 0.2307692308,
      "stl_g": 0.1538461538,
      "blk_g": 0,
      "tov_g": 0.2307692308,
      "pf_g": 0.3076923077,
      "pts_g": 1.1538461538
    },
    {
      "season": "2023-24",
      "team": "Akron",
      "conf": "MAC",
      "gp": 5,
      "gs": 0,
      "mp_g": 4.4,
      "fg_pct": 0.2,
      "fg3_pct": 0.1,
      "ft_pct": 0.5,
      "orb_g": 0,
      "drb_g": 0.4,
      "trb_g": 0.4,
      "ast_g": 0,
      "stl_g": 0.4,
      "blk_g": 0,
      "tov_g": 0,
      "pf_g": 0.4,
      "pts_g": 1.6
    },
    {
      "season": "2024-25",
      "team": "Akron",
      "conf": "MAC",
      "gp": 10,
      "gs": 1,
      "mp_g": 3.7,
      "fg_pct": 0.3043478261,
      "fg3_pct": 0.2380952381,
      "ft_pct": 0.75,
      "orb_g": 0,
      "drb_g": 0.2,
      "trb_g": 0.2,
      "ast_g": 0,
      "stl_g": 0.1,
      "blk_g": 0,
      "tov_g": 0.1,
      "pf_g": 0.1,
      "pts_g": 2.2
    }
  ],
  "source": "https://www.sports-reference.com/cbb/players/evan-wilson-1.html",
  "last_scraped": "2025-11-01T15:06:11.030Z"
}