{
  "slug": "jarred-hyder-1",
  "name": "Jarred Hyder",
  "seasons": [
    {
      "season": "2019-20",
      "team": "Fresno State",
      "conf": "MWC",
      "gp": 26,
      "gs": 24,
      "mp_g": 31.9230769231,
      "fg_pct": 0.3802816901,
      "fg3_pct": 0.3020833333,
      "ft_pct": 0.8333333333,
      "orb_g": 0.4230769231,
      "drb_g": 2.1923076923,
      "trb_g": 2.6153846154,
      "ast_g": 3.1153846154,
      "stl_g": 0.5,
      "blk_g": 0.1153846154,
      "tov_g": 2.5384615385,
      "pf_g": 1.6923076923,
      "pts_g": 9.0769230769
    },
    {
      "season": "2020-21",
      "team": "California",
      "conf": "Pac-12",
      "gp": 21,
      "gs": 4,
      "mp_g": 16.1904761905,
      "fg_pct": 0.3653846154,
      "fg3_pct": 0.2272727273,
      "ft_pct": 0.7179487179,
      "orb_g": 0.1428571429,
      "drb_g": 1.0476190476,
      "trb_g": 1.1904761905,
      "ast_g": 1.8095238095,
      "stl_g": 0.2380952381,
      "blk_g": 0.0952380952,
      "tov_g": 1.3333333333,
      "pf_g": 1.3333333333,
      "pts_g": 5.4285714286
    },
    {
      "season": "2021-22",
      "team": "California",
      "conf": "Pac-12",
      "gp": 22,
      "gs": 2,
      "mp_g": 8.8181818182,
      "fg_pct": 0.2368421053,
      "fg3_pct": 0.1875,
      "ft_pct": 0.7272727273,
      "orb_g": 0.0454545455,
      "drb_g": 0.5909090909,
      "trb_g": 0.6363636364,
      "ast_g": 0.8181818182,
      "stl_g": 0.1363636364,
      "blk_g": 0.0454545455,
      "tov_g": 0.4090909091,
      "pf_g": 0.5,
      "pts_g": 1.3181818182
    },
    {
      "season": "2022-23",
      "team": "Did not play - injury/redshirt",
      "conf": "—",
      "gp": null,
      "gs": null,
      "mp_g": null,
      "fg_pct": null,
      "fg3_pct": null,
      "ft_pct": null,
      "orb_g": null,
      "drb_g": null,
      "trb_g": null,
      "ast_g": null,
      "stl_g": null,
      "blk_g": null,
      "tov_g": null,
      "pf_g": null,
      "pts_g": null
    },
    {
      "season": "2023-24",
      "team": "Cal Poly",
      "conf": "Big West",
      "gp": 25,
      "gs": 25,
      "mp_g": 33.96,
      "fg_pct": 0.3246268657,
      "fg3_pct": 0.3178807947,
      "ft_pct": 0.8372093023,
      "orb_g": 0.4,
      "drb_g": 2.24,
      "trb_g": 2.64,
      "ast_g": 2.48,
      "stl_g": 1.24,
      "blk_g": 0.2,
      "tov_g": 2.08,
      "pf_g": 1.76,
      "pts_g": 10.32
    },
    {
      "season": "2024-25",
      "team": "Cal Poly",
      "conf": "Big West",
      "gp": 33,
      "gs": 33,
      "mp_g": 32.8484848485,
      "fg_pct": 0.3980582524,
      "fg3_pct": 0.3548387097,
      "ft_pct": 0.796875,
      "orb_g": 0.5757575758,
      "drb_g": 2.8787878788,
      "trb_g": 3.4545454545,
      "ast_g": 3.1818181818,
      "stl_g": 1.2424242424,
      "blk_g": 0,
      "tov_g": 2.5151515152,
      "pf_g": 1.4848484848,
      "pts_g": 14.4848484848
    }
  ],
  "source": "https://www.sports-reference.com/cbb/players/jarred-hyder-1.html",
  "last_scraped": "2025-11-01T04:42:38.328Z"
}