{
  "slug": "jayshayne-woodard-1",
  "name": "Jayshayne Woodard",
  "seasons": [
    {
      "season": "2022-23",
      "team": "Did not play - juco",
      "conf": "—",
      "gp": null,
      "gs": null,
      "mp_g": null,
      "fg_pct": null,
      "fg3_pct": null,
      "ft_pct": null,
      "orb_g": null,
      "drb_g": null,
      "trb_g": null,
      "ast_g": null,
      "stl_g": null,
      "blk_g": null,
      "tov_g": null,
      "pf_g": null,
      "pts_g": null
    },
    {
      "season": "2023-24",
      "team": "Did not play - juco",
      "conf": "—",
      "gp": null,
      "gs": null,
      "mp_g": null,
      "fg_pct": null,
      "fg3_pct": null,
      "ft_pct": null,
      "orb_g": null,
      "drb_g": null,
      "trb_g": null,
      "ast_g": null,
      "stl_g": null,
      "blk_g": null,
      "tov_g": null,
      "pf_g": null,
      "pts_g": null
    },
    {
      "season": "2024-25",
      "team": "East Carolina",
      "conf": "AAC",
      "gp": 33,
      "gs": 9,
      "mp_g": 21.4242424242,
      "fg_pct": 0.4358974359,
      "fg3_pct": 0.2903225806,
      "ft_pct": 0.6486486486,
      "orb_g": 1.4848484848,
      "drb_g": 2.5757575758,
      "trb_g": 4.0606060606,
      "ast_g": 1.9090909091,
      "stl_g": 1.1818181818,
      "blk_g": 0.9090909091,
      "tov_g": 1.4242424242,
      "pf_g": 2.2727272727,
      "pts_g": 5.8484848485
    }
  ],
  "source": "https://www.sports-reference.com/cbb/players/jayshayne-woodard-1.html",
  "last_scraped": "2025-11-01T04:42:56.731Z"
}