{
  "slug": "josh-gray-2",
  "name": "Josh Gray",
  "seasons": [
    {
      "season": "2020-21",
      "team": "Louisiana State",
      "conf": "SEC",
      "gp": 10,
      "gs": 0,
      "mp_g": 3.3,
      "fg_pct": 0.5,
      "fg3_pct": null,
      "ft_pct": 0.2857142857,
      "orb_g": 0.5,
      "drb_g": 0.7,
      "trb_g": 1.2,
      "ast_g": 0,
      "stl_g": 0,
      "blk_g": 0.1,
      "tov_g": 0.2,
      "pf_g": 0.7,
      "pts_g": 0.8
    },
    {
      "season": "2021-22",
      "team": "South Carolina",
      "conf": "SEC",
      "gp": 25,
      "gs": 3,
      "mp_g": 11.36,
      "fg_pct": 0.5084745763,
      "fg3_pct": 0,
      "ft_pct": 0.3823529412,
      "orb_g": 1.44,
      "drb_g": 2.04,
      "trb_g": 3.48,
      "ast_g": 0.36,
      "stl_g": 0.44,
      "blk_g": 0.68,
      "tov_g": 0.48,
      "pf_g": 1.48,
      "pts_g": 2.92
    },
    {
      "season": "2022-23",
      "team": "South Carolina",
      "conf": "SEC",
      "gp": 32,
      "gs": 15,
      "mp_g": 16.78125,
      "fg_pct": 0.5135135135,
      "fg3_pct": 0,
      "ft_pct": 0.4615384615,
      "orb_g": 2.6875,
      "drb_g": 3.59375,
      "trb_g": 6.28125,
      "ast_g": 0.46875,
      "stl_g": 0.28125,
      "blk_g": 0.84375,
      "tov_g": 0.96875,
      "pf_g": 2.3125,
      "pts_g": 4.3125
    },
    {
      "season": "2023-24",
      "team": "South Carolina",
      "conf": "SEC",
      "gp": 31,
      "gs": 0,
      "mp_g": 9.9677419355,
      "fg_pct": 0.5428571429,
      "fg3_pct": null,
      "ft_pct": 0.4897959184,
      "orb_g": 0.9032258065,
      "drb_g": 1.9032258065,
      "trb_g": 2.8064516129,
      "ast_g": 0.4516129032,
      "stl_g": 0.0967741935,
      "blk_g": 0.5806451613,
      "tov_g": 0.6451612903,
      "pf_g": 1.5806451613,
      "pts_g": 3.2258064516
    },
    {
      "season": "2024-25",
      "team": "Missouri",
      "conf": "SEC",
      "gp": 33,
      "gs": 16,
      "mp_g": 15.5151515152,
      "fg_pct": 0.53125,
      "fg3_pct": 0.3333333333,
      "ft_pct": 0.5692307692,
      "orb_g": 1.8181818182,
      "drb_g": 3.4545454545,
      "trb_g": 5.2727272727,
      "ast_g": 0.5757575758,
      "stl_g": 0.303030303,
      "blk_g": 0.4242424242,
      "tov_g": 0.8787878788,
      "pf_g": 2.3939393939,
      "pts_g": 3.2121212121
    }
  ],
  "source": "https://www.sports-reference.com/cbb/players/josh-gray-2.html",
  "last_scraped": "2025-11-01T00:45:35.670Z"
}