{
  "slug": "matteus-case-1",
  "name": "Matteus Case",
  "seasons": [
    {
      "season": "2021-22",
      "team": "Providence",
      "conf": "Big East",
      "gp": 4,
      "gs": 0,
      "mp_g": 1.5,
      "fg_pct": 1,
      "fg3_pct": null,
      "ft_pct": 0,
      "orb_g": 0,
      "drb_g": 0.5,
      "trb_g": 0.5,
      "ast_g": 0,
      "stl_g": 0,
      "blk_g": 0,
      "tov_g": 0.25,
      "pf_g": 0,
      "pts_g": 1
    },
    {
      "season": "2022-23",
      "team": "William & Mary",
      "conf": "CAA",
      "gp": 33,
      "gs": 9,
      "mp_g": 21.2727272727,
      "fg_pct": 0.3540372671,
      "fg3_pct": 0.2638888889,
      "ft_pct": 0.65,
      "orb_g": 0.6666666667,
      "drb_g": 2.5151515152,
      "trb_g": 3.1818181818,
      "ast_g": 1.0303030303,
      "stl_g": 0.5151515152,
      "blk_g": 0.0909090909,
      "tov_g": 0.5454545455,
      "pf_g": 1.3333333333,
      "pts_g": 4.8181818182
    },
    {
      "season": "2023-24",
      "team": "William & Mary",
      "conf": "CAA",
      "gp": 25,
      "gs": 8,
      "mp_g": 25.92,
      "fg_pct": 0.3963414634,
      "fg3_pct": 0.25,
      "ft_pct": 0.5918367347,
      "orb_g": 1.12,
      "drb_g": 2.84,
      "trb_g": 3.96,
      "ast_g": 1.4,
      "stl_g": 0.72,
      "blk_g": 0.04,
      "tov_g": 1.12,
      "pf_g": 1.92,
      "pts_g": 6.84
    },
    {
      "season": "2024-25",
      "team": "William & Mary",
      "conf": "CAA",
      "gp": 32,
      "gs": 14,
      "mp_g": 21.75,
      "fg_pct": 0.4603174603,
      "fg3_pct": 0.2807017544,
      "ft_pct": 0.7346938776,
      "orb_g": 0.59375,
      "drb_g": 1.9375,
      "trb_g": 2.53125,
      "ast_g": 2.03125,
      "stl_g": 0.84375,
      "blk_g": 0,
      "tov_g": 1.84375,
      "pf_g": 1.34375,
      "pts_g": 8.1875
    }
  ],
  "source": "https://www.sports-reference.com/cbb/players/matteus-case-1.html",
  "last_scraped": "2025-11-01T13:53:05.949Z"
}