{
  "slug": "milos-uzan-1",
  "name": "Milos Uzan",
  "seasons": [
    {
      "season": "2022-23",
      "team": "Oklahoma",
      "conf": "Big 12",
      "gp": 32,
      "gs": 24,
      "mp_g": 28.625,
      "fg_pct": 0.47,
      "fg3_pct": 0.4084507042,
      "ft_pct": 0.7647058824,
      "orb_g": 0.1875,
      "drb_g": 2.53125,
      "trb_g": 2.71875,
      "ast_g": 3,
      "stl_g": 0.75,
      "blk_g": 0.1875,
      "tov_g": 2.15625,
      "pf_g": 2.125,
      "pts_g": 7.59375
    },
    {
      "season": "2023-24",
      "team": "Oklahoma",
      "conf": "Big 12",
      "gp": 32,
      "gs": 32,
      "mp_g": 31.6875,
      "fg_pct": 0.3917525773,
      "fg3_pct": 0.2956521739,
      "ft_pct": 0.6756756757,
      "orb_g": 0.25,
      "drb_g": 3.15625,
      "trb_g": 3.40625,
      "ast_g": 4.40625,
      "stl_g": 1.1875,
      "blk_g": 0.28125,
      "tov_g": 2.03125,
      "pf_g": 1.59375,
      "pts_g": 8.96875
    },
    {
      "season": "2024-25",
      "team": "Houston",
      "conf": "Big 12",
      "gp": 40,
      "gs": 40,
      "mp_g": 31.525,
      "fg_pct": 0.4528795812,
      "fg3_pct": 0.4275862069,
      "ft_pct": 0.7833333333,
      "orb_g": 0.35,
      "drb_g": 2.7,
      "trb_g": 3.05,
      "ast_g": 4.25,
      "stl_g": 0.9,
      "blk_g": 0.075,
      "tov_g": 1.425,
      "pf_g": 2,
      "pts_g": 11.375
    }
  ],
  "source": "https://www.sports-reference.com/cbb/players/milos-uzan-1.html",
  "last_scraped": "2025-11-01T00:50:46.494Z"
}