{
  "slug": "nijel-pack-1",
  "name": "Nijel Pack",
  "seasons": [
    {
      "season": "2020-21",
      "team": "Kansas State",
      "conf": "Big 12",
      "gp": 24,
      "gs": 24,
      "mp_g": 33.4583333333,
      "fg_pct": 0.4176245211,
      "fg3_pct": 0.4054054054,
      "ft_pct": 0.7941176471,
      "orb_g": 0.5833333333,
      "drb_g": 3.0833333333,
      "trb_g": 3.6666666667,
      "ast_g": 3.7916666667,
      "stl_g": 1.1666666667,
      "blk_g": 0,
      "tov_g": 2.0416666667,
      "pf_g": 2.0416666667,
      "pts_g": 12.7083333333
    },
    {
      "season": "2021-22",
      "team": "Kansas State",
      "conf": "Big 12",
      "gp": 29,
      "gs": 28,
      "mp_g": 33.1034482759,
      "fg_pct": 0.4545454545,
      "fg3_pct": 0.4357798165,
      "ft_pct": 0.8450704225,
      "orb_g": 0.7586206897,
      "drb_g": 3.0344827586,
      "trb_g": 3.7931034483,
      "ast_g": 2.2413793103,
      "stl_g": 1.3448275862,
      "blk_g": 0.1034482759,
      "tov_g": 1.4827586207,
      "pf_g": 1.6896551724,
      "pts_g": 17.4137931034
    },
    {
      "season": "2022-23",
      "team": "Miami (FL)",
      "conf": "ACC",
      "gp": 35,
      "gs": 35,
      "mp_g": 31.6,
      "fg_pct": 0.4413265306,
      "fg3_pct": 0.4037558685,
      "ft_pct": 0.8823529412,
      "orb_g": 0.5714285714,
      "drb_g": 2.1428571429,
      "trb_g": 2.7142857143,
      "ast_g": 2.3142857143,
      "stl_g": 0.9714285714,
      "blk_g": 0.1714285714,
      "tov_g": 1.6857142857,
      "pf_g": 1.5142857143,
      "pts_g": 13.6285714286
    },
    {
      "season": "2023-24",
      "team": "Miami (FL)",
      "conf": "ACC",
      "gp": 25,
      "gs": 25,
      "mp_g": 32.48,
      "fg_pct": 0.4,
      "fg3_pct": 0.3571428571,
      "ft_pct": 0.7647058824,
      "orb_g": 0.36,
      "drb_g": 2.2,
      "trb_g": 2.56,
      "ast_g": 3.56,
      "stl_g": 0.96,
      "blk_g": 0.28,
      "tov_g": 1.76,
      "pf_g": 1.04,
      "pts_g": 13.32
    },
    {
      "season": "2024-25",
      "team": "Miami (FL)",
      "conf": "ACC",
      "gp": 9,
      "gs": 9,
      "mp_g": 31.2222222222,
      "fg_pct": 0.4536082474,
      "fg3_pct": 0.3859649123,
      "ft_pct": 0.8333333333,
      "orb_g": 0.8888888889,
      "drb_g": 2.1111111111,
      "trb_g": 3,
      "ast_g": 4.3333333333,
      "stl_g": 0.4444444444,
      "blk_g": 0.1111111111,
      "tov_g": 1.3333333333,
      "pf_g": 1.6666666667,
      "pts_g": 13.8888888889
    }
  ],
  "source": "https://www.sports-reference.com/cbb/players/nijel-pack-1.html",
  "last_scraped": "2025-11-01T00:51:36.891Z"
}