{
  "slug": "noah-farrakhan-1",
  "name": "Noah Farrakhan",
  "seasons": [
    {
      "season": "2020-21",
      "team": "East Carolina",
      "conf": "AAC",
      "gp": 12,
      "gs": 0,
      "mp_g": 10.0833333333,
      "fg_pct": 0.4,
      "fg3_pct": 0.3333333333,
      "ft_pct": 0.75,
      "orb_g": 0.0833333333,
      "drb_g": 0.8333333333,
      "trb_g": 0.9166666667,
      "ast_g": 1,
      "stl_g": 0.1666666667,
      "blk_g": 0,
      "tov_g": 0.8333333333,
      "pf_g": 0.75,
      "pts_g": 3
    },
    {
      "season": "2021-22",
      "team": "Eastern Michigan",
      "conf": "MAC",
      "gp": 26,
      "gs": 25,
      "mp_g": 31.4230769231,
      "fg_pct": 0.4262734584,
      "fg3_pct": 0.4077669903,
      "ft_pct": 0.7578947368,
      "orb_g": 0.7307692308,
      "drb_g": 3.1153846154,
      "trb_g": 3.8461538462,
      "ast_g": 2.3461538462,
      "stl_g": 1.1538461538,
      "blk_g": 0.1923076923,
      "tov_g": 3,
      "pf_g": 2.1538461538,
      "pts_g": 16.6153846154
    },
    {
      "season": "2022-23",
      "team": "Eastern Michigan",
      "conf": "MAC",
      "gp": 31,
      "gs": 28,
      "mp_g": 30.2903225806,
      "fg_pct": 0.4319526627,
      "fg3_pct": 0.243902439,
      "ft_pct": 0.7529411765,
      "orb_g": 0.5483870968,
      "drb_g": 3.5161290323,
      "trb_g": 4.064516129,
      "ast_g": 2.2580645161,
      "stl_g": 0.6774193548,
      "blk_g": 0.1290322581,
      "tov_g": 2.2258064516,
      "pf_g": 3.1290322581,
      "pts_g": 12.1290322581
    },
    {
      "season": "2023-24",
      "team": "West Virginia",
      "conf": "Big 12",
      "gp": 23,
      "gs": 5,
      "mp_g": 19.8260869565,
      "fg_pct": 0.4085365854,
      "fg3_pct": 0.3513513514,
      "ft_pct": 0.75,
      "orb_g": 0.3913043478,
      "drb_g": 2.6086956522,
      "trb_g": 3,
      "ast_g": 1.6956521739,
      "stl_g": 0.4782608696,
      "blk_g": 0.0434782609,
      "tov_g": 1.4782608696,
      "pf_g": 2.3043478261,
      "pts_g": 7.6956521739
    },
    {
      "season": "2024-25",
      "team": "Hampton",
      "conf": "CAA",
      "gp": 31,
      "gs": 23,
      "mp_g": 29.4193548387,
      "fg_pct": 0.4297082228,
      "fg3_pct": 0.3225806452,
      "ft_pct": 0.7653061224,
      "orb_g": 0.7419354839,
      "drb_g": 2.2903225806,
      "trb_g": 3.0322580645,
      "ast_g": 2.6774193548,
      "stl_g": 1.2580645161,
      "blk_g": 0.1290322581,
      "tov_g": 1.5483870968,
      "pf_g": 2.9032258065,
      "pts_g": 14.1612903226
    }
  ],
  "source": "https://www.sports-reference.com/cbb/players/noah-farrakhan-1.html",
  "last_scraped": "2025-11-01T13:53:30.077Z"
}