{
  "slug": "sion-james-1",
  "name": "Sion James",
  "seasons": [
    {
      "season": "2020-21",
      "team": "Tulane",
      "conf": "AAC",
      "gp": 23,
      "gs": 17,
      "mp_g": 25.9565217391,
      "fg_pct": 0.431372549,
      "fg3_pct": 0.28,
      "ft_pct": 0.65,
      "orb_g": 0.4782608696,
      "drb_g": 3.0434782609,
      "trb_g": 3.5217391304,
      "ast_g": 1.9130434783,
      "stl_g": 1.2173913043,
      "blk_g": 0.2173913043,
      "tov_g": 1.6956521739,
      "pf_g": 2.2173913043,
      "pts_g": 5.8260869565
    },
    {
      "season": "2021-22",
      "team": "Tulane",
      "conf": "AAC",
      "gp": 29,
      "gs": 28,
      "mp_g": 35.1724137931,
      "fg_pct": 0.4090909091,
      "fg3_pct": 0.3333333333,
      "ft_pct": 0.7027027027,
      "orb_g": 0.4482758621,
      "drb_g": 3.8275862069,
      "trb_g": 4.275862069,
      "ast_g": 3.5862068966,
      "stl_g": 1.5862068966,
      "blk_g": 0.4827586207,
      "tov_g": 1.5862068966,
      "pf_g": 2.4137931034,
      "pts_g": 7.4137931034
    },
    {
      "season": "2022-23",
      "team": "Tulane",
      "conf": "AAC",
      "gp": 31,
      "gs": 31,
      "mp_g": 37.0967741935,
      "fg_pct": 0.4834123223,
      "fg3_pct": 0.3170731707,
      "ft_pct": 0.71,
      "orb_g": 0.6774193548,
      "drb_g": 4.1290322581,
      "trb_g": 4.8064516129,
      "ast_g": 3.3870967742,
      "stl_g": 2.0322580645,
      "blk_g": 0.8064516129,
      "tov_g": 1.2258064516,
      "pf_g": 2.9032258065,
      "pts_g": 9.7096774194
    },
    {
      "season": "2023-24",
      "team": "Tulane",
      "conf": "AAC",
      "gp": 31,
      "gs": 31,
      "mp_g": 36.7419354839,
      "fg_pct": 0.5138888889,
      "fg3_pct": 0.3805309735,
      "ft_pct": 0.6834532374,
      "orb_g": 0.9677419355,
      "drb_g": 4.3870967742,
      "trb_g": 5.3548387097,
      "ast_g": 2.7096774194,
      "stl_g": 1.6129032258,
      "blk_g": 0.7419354839,
      "tov_g": 1.1935483871,
      "pf_g": 2.6129032258,
      "pts_g": 14
    },
    {
      "season": "2024-25",
      "team": "Duke",
      "conf": "ACC",
      "gp": 39,
      "gs": 32,
      "mp_g": 25.5384615385,
      "fg_pct": 0.5161290323,
      "fg3_pct": 0.4133333333,
      "ft_pct": 0.81,
      "orb_g": 0.7435897436,
      "drb_g": 3.4358974359,
      "trb_g": 4.1794871795,
      "ast_g": 2.9487179487,
      "stl_g": 0.8205128205,
      "blk_g": 0.2564102564,
      "tov_g": 1.2051282051,
      "pf_g": 2.0256410256,
      "pts_g": 8.6153846154
    }
  ],
  "source": "https://www.sports-reference.com/cbb/players/sion-james-1.html",
  "last_scraped": "2025-11-01T00:54:49.025Z"
}