{
  "slug": "zaakir-williamson-1",
  "name": "Zaakir Williamson",
  "seasons": [
    {
      "season": "2022-23",
      "team": "Buffalo",
      "conf": "MAC",
      "gp": 18,
      "gs": 0,
      "mp_g": 3.6666666667,
      "fg_pct": 0.6,
      "fg3_pct": null,
      "ft_pct": 0.8,
      "orb_g": 0.1111111111,
      "drb_g": 0.9444444444,
      "trb_g": 1.0555555556,
      "ast_g": 0.3333333333,
      "stl_g": 0.1111111111,
      "blk_g": 0.1111111111,
      "tov_g": 0.4444444444,
      "pf_g": 0.3333333333,
      "pts_g": 1.1111111111
    },
    {
      "season": "2023-24",
      "team": "Buffalo",
      "conf": "MAC",
      "gp": 26,
      "gs": 4,
      "mp_g": 12.3076923077,
      "fg_pct": 0.6935483871,
      "fg3_pct": 0,
      "ft_pct": 0.65,
      "orb_g": 1.2307692308,
      "drb_g": 1.4615384615,
      "trb_g": 2.6923076923,
      "ast_g": 0.6153846154,
      "stl_g": 0.2307692308,
      "blk_g": 0.4230769231,
      "tov_g": 0.8461538462,
      "pf_g": 1.1538461538,
      "pts_g": 3.8076923077
    },
    {
      "season": "2024-25",
      "team": "Saint Peter's",
      "conf": "MAAC",
      "gp": 24,
      "gs": 6,
      "mp_g": 14.875,
      "fg_pct": 0.4,
      "fg3_pct": 0.2,
      "ft_pct": 0.7058823529,
      "orb_g": 1.5416666667,
      "drb_g": 1.7083333333,
      "trb_g": 3.25,
      "ast_g": 0.3333333333,
      "stl_g": 0.2083333333,
      "blk_g": 0.6666666667,
      "tov_g": 0.5833333333,
      "pf_g": 1.875,
      "pts_g": 4.9166666667
    }
  ],
  "source": "https://www.sports-reference.com/cbb/players/zaakir-williamson-1.html",
  "last_scraped": "2025-11-01T15:02:04.206Z"
}